KailWeb/__init__.py
KailWeb/KailWeb/__init__.py
KailWeb/KailWeb/index.py
KailWeb/test/__init__.py
KailWeb/test/test_index.py
KailWeb-0.5.dist-info/LICENSE
KailWeb-0.5.dist-info/METADATA
KailWeb-0.5.dist-info/WHEEL
KailWeb-0.5.dist-info/top_level.txt
KailWeb-0.5.dist-info/RECORD
