Metadata-Version: 2.1
Name: KailWeb
Version: 0.5
Summary: KailWeb - framework to creating site on HTML5
Home-page: 
Author: Syirezz(KailUser, Colin)
Author-email: 
License: MIT
License-File: LICENSE
